rel_easy/__init__.py
rel_easy/cli.py
rel_easy/consts.py
rel_easy/releasy_pkg_data.py
rel_easy/semversion.py
rel_easy/util.py
rel_easy/version.py
rel_easy/DATA/github-deploy-action-yml.tmpl
rel_easy/DATA/pypirc.tmpl
rel_easy/DATA/setup_py.tmpl
rel_easy/DATA/version.tmpl
rel_easy-0.0.4.dist-info/METADATA
rel_easy-0.0.4.dist-info/WHEEL
rel_easy-0.0.4.dist-info/entry_points.txt
rel_easy-0.0.4.dist-info/top_level.txt
rel_easy-0.0.4.dist-info/RECORD
