Metadata-Version: 2.1
Name: rel-easy
Version: 0.0.4
Summary: Help with versioning and release to pypi of projects
Home-page: https://github.com/joranbeasley/rel-easy
Author: Joran Beasley
Author-email: joranbeasley@gmail.com
License: UNKNOWN
Platform: UNKNOWN
Classifier: Programming Language :: Python :: 3
Classifier: License :: OSI Approved :: MIT License
Classifier: Operating System :: OS Independent
Requires-Python: >=2.7
Requires-Dist: click (==7.0.0)
Requires-Dist: six
Requires-Dist: twine
